jsonlite/__init__.py
jsonlite/jsonlite.py
jsonlite/monkey_patch.py
tests/__init__.py
tests/test_basic.py
tests/test_binary.py
tests/test_concurrency.py
tests/test_data_integrity.py
tests/test_datatime.py
tests/test_number.py
tests/test_performance.py
tests/test_pymongo_compat.py
jsonlite-0.0.11.dist-info/LICENSE
jsonlite-0.0.11.dist-info/METADATA
jsonlite-0.0.11.dist-info/WHEEL
jsonlite-0.0.11.dist-info/top_level.txt
jsonlite-0.0.11.dist-info/RECORD
