Metadata-Version: 2.1
Name: jsonlite
Version: 0.0.11
Summary: A lightweight local JSON database
Home-page: https://github.com/simpx/jsonlite
Author: simpx
Author-email: simpxx@gmail.com
License: MIT
Classifier: Development Status :: 3 - Alpha
Classifier: Intended Audience :: Developers
Classifier: License :: OSI Approved :: MIT License
Classifier: Programming Language :: Python :: 3
Classifier: Programming Language :: Python :: 3.6
Classifier: Programming Language :: Python :: 3.7
Classifier: Programming Language :: Python :: 3.8
Classifier: Programming Language :: Python :: 3.9
License-File: LICENSE
